odoo/addons/event_sale_track/README.rst
odoo/addons/event_sale_track/__init__.py
odoo/addons/event_sale_track/__manifest__.py
odoo/addons/event_sale_track/i18n/event_sale_track.pot
odoo/addons/event_sale_track/i18n/event_track_ticket.pot
odoo/addons/event_sale_track/i18n/fr.po
odoo/addons/event_sale_track/models/__init__.py
odoo/addons/event_sale_track/models/event_registration.py
odoo/addons/event_sale_track/models/event_ticket.py
odoo/addons/event_sale_track/models/event_track.py
odoo/addons/event_sale_track/readme/CONTRIBUTORS.rst
odoo/addons/event_sale_track/readme/DESCRIPTION.rst
odoo/addons/event_sale_track/readme/ROADMAP.rst
odoo/addons/event_sale_track/readme/USAGE.rst
odoo/addons/event_sale_track/readme/images/track_view.png
odoo/addons/event_sale_track/readme/images/website_tickets.png
odoo/addons/event_sale_track/static/description/icon.png
odoo/addons/event_sale_track/static/description/index.html
odoo/addons/event_sale_track/tests/__init__.py
odoo/addons/event_sale_track/tests/test_registration.py
odoo/addons/event_sale_track/tests/test_sale_order.py
odoo/addons/event_sale_track/tests/test_ticket.py
odoo/addons/event_sale_track/tests/test_track.py
odoo/addons/event_sale_track/views/event_registration.xml
odoo/addons/event_sale_track/views/event_ticket.xml
odoo/addons/event_sale_track/views/event_track.xml
odoo/addons/event_sale_track/views/event_views.xml
odoo11_addon_event_sale_track-11.0.1.0.0.99.dev4.dist-info/METADATA
odoo11_addon_event_sale_track-11.0.1.0.0.99.dev4.dist-info/WHEEL
odoo11_addon_event_sale_track-11.0.1.0.0.99.dev4.dist-info/top_level.txt
odoo11_addon_event_sale_track-11.0.1.0.0.99.dev4.dist-info/RECORD
